LICENSE
MANIFEST.in
README.rst
setup.py
shfd.py
test_multi_shfd.py
test_shfd.py
shfd.egg-info/PKG-INFO
shfd.egg-info/SOURCES.txt
shfd.egg-info/dependency_links.txt
shfd.egg-info/top_level.txt