Metadata-Version: 1.0
Name: shfd
Version: 0.1
Summary: Sh for dummies
Home-page: https://github.com/morgotth/shfd
Author: Morgotth
Author-email: morgotth0@gmail.com
License: Beerware
Platform: any
Classifier: Development Status :: 4 - Beta
Classifier: Intended Audience :: Developers
Classifier: Natural Language :: English
Classifier: License :: Freeware
Classifier: Programming Language :: Python
Classifier: Programming Language :: Python :: 2.6
Classifier: Programming Language :: Python :: 2.7
Classifier: Programming Language :: Python :: 3.0
Classifier: Programming Language :: Python :: 3.1
Classifier: Programming Language :: Python :: 3.2
Classifier: Programming Language :: Python :: 3.3
